{"entities":[{"children":[],"components":[{"data":{"name":"Camera"},"type":"Identification"},{"data":{"position":{"x":-2.4617385864257813,"y":6.87842321395874,"z":21.61644744873047},"previousPosition":{"x":-2.4617385864257813,"y":6.87842321395874,"z":21.61644744873047},"previousRotation":{"x":9.999545097351074,"y":-697.4205932617188,"z":0.0},"previousScale":{"x":1.0,"y":1.0,"z":1.0},"rotation":{"x":9.999545097351074,"y":-697.4205932617188,"z":0.0},"scale":{"x":1.0,"y":1.0,"z":1.0}},"type":"Transform"},{"data":{"diff_coeff":{"x":0.0,"y":0.0996391698718071,"z":0.977707028388977},"meshName":"Cube","selected":false,"spec_coeff":{"x":0.5,"y":0.5,"z":0.5},"spec_exponent":0.0},"type":"Material"},{"data":{"aspect":1.4358974695205688,"back":{"x":-0.378131240606308,"y":0.17364035546779633,"z":0.909321665763855},"farPlane":1000.0,"fov":80.0,"nearPlane":0.0010000000474974513,"renderTarget":0,"renderTargetType":0,"right":{"x":0.923348069190979,"y":0.0,"z":0.3839639723300934},"up":{"x":0.06667163968086243,"y":0.984809160232544,"z":-0.16033048927783966}},"type":"Camera"}],"id":0},{"children":[],"components":[{"data":{"name":"Floor"},"type":"Identification"},{"data":{"position":{"x":1.9193458557128906,"y":0.0,"z":-3.1178436279296875},"previousPosition":{"x":1.9193458557128906,"y":0.0,"z":-3.1178436279296875},"previousRotation":{"x":0.0,"y":-0.0,"z":0.0},"previousScale":{"x":8.0,"y":1.0,"z":8.0},"rotation":{"x":0.0,"y":-0.0,"z":0.0},"scale":{"x":8.0,"y":1.0,"z":8.0}},"type":"Transform"},{"data":{"diff_coeff":{"x":2.0,"y":2.0,"z":2.0},"meshName":"Cube","selected":false,"spec_coeff":{"x":0.5,"y":0.5,"z":0.5},"spec_exponent":5.0},"type":"Material"},{"data":{"texturePath":"assets\\textures\\Checker.jpg"},"type":"Texture"}],"id":1},{"children":[],"components":[{"data":{"name":"Fox Box"},"type":"Identification"},{"data":{"position":{"x":-3.2912163734436035,"y":4.828322410583496,"z":-0.3366219401359558},"previousPosition":{"x":-3.2912163734436035,"y":4.828322410583496,"z":-0.3366219401359558},"previousRotation":{"x":0.0,"y":54282.421875,"z":54255.4921875},"previousScale":{"x":1.0,"y":1.0,"z":1.0},"rotation":{"x":0.0,"y":54282.421875,"z":54255.4921875},"scale":{"x":1.0,"y":1.0,"z":1.0}},"type":"Transform"},{"data":{"acceleration":{"x":0.0,"y":0.0,"z":0.0},"rotationalAcceleration":{"x":0.0,"y":0.0,"z":0.0},"rotationalVelocity":{"x":0.0,"y":10.0,"z":10.0},"velocity":{"x":0.0,"y":0.0,"z":0.0}},"type":"RigidBody"},{"data":{"diff_coeff":{"x":2.0,"y":2.0,"z":2.0},"meshName":"Cube","selected":false,"spec_coeff":{"x":0.5,"y":0.5,"z":0.5},"spec_exponent":5.0},"type":"Material"},{"data":{"texturePath":"assets\\textures\\Fox.jpg"},"type":"Texture"}],"id":2},{"children":[],"components":[{"data":{"name":"Spinning Kurisu"},"type":"Identification"},{"data":{"position":{"x":0.27633416652679443,"y":6.517978668212891,"z":-2.0177035331726074},"previousPosition":{"x":0.27633416652679443,"y":6.517978668212891,"z":-2.0177035331726074},"previousRotation":{"x":0.0,"y":2022607.625,"z":0.0},"previousScale":{"x":0.9998350739479065,"y":1.999997854232788,"z":0.9998350739479065},"rotation":{"x":0.0,"y":2022607.625,"z":0.0},"scale":{"x":0.9998350739479065,"y":1.999997854232788,"z":0.9998350739479065}},"type":"Transform"},{"data":{"acceleration":{"x":0.0,"y":0.0,"z":0.0},"rotationalAcceleration":{"x":0.0,"y":0.0,"z":0.0},"rotationalVelocity":{"x":0.0,"y":360.0,"z":0.0},"velocity":{"x":0.0,"y":0.0,"z":0.0}},"type":"RigidBody"},{"data":{"diff_coeff":{"x":0.5477707386016846,"y":1.0,"z":0.0},"meshName":"Cube","selected":false,"spec_coeff":{"x":0.0,"y":1.0,"z":0.02547764778137207},"spec_exponent":50.0},"type":"Material"},{"data":{"texturePath":"assets\\textures\\Kurisu.png"},"type":"Texture"}],"id":3},{"children":[],"components":[{"data":{"name":"Center Light"},"type":"Identification"},{"data":{"position":{"x":3.3459999561309814,"y":11.699999809265137,"z":-1.7999999523162842},"previousPosition":{"x":3.3459999561309814,"y":11.699999809265137,"z":-1.7999999523162842},"previousRotation":{"x":0.0,"y":-0.0,"z":0.0},"previousScale":{"x":0.10000000149011612,"y":0.10000000149011612,"z":0.10000000149011612},"rotation":{"x":0.0,"y":-0.0,"z":0.0},"scale":{"x":0.10000000149011612,"y":0.10000000149011612,"z":0.10000000149011612}},"type":"Transform"},{"data":{"diff_coeff":{"x":2.0,"y":2.0,"z":2.0},"meshName":"Cube","selected":false,"spec_coeff":{"x":0.5,"y":0.5,"z":0.5},"spec_exponent":5.0},"type":"Material"},{"data":{"color":{"x":1.0,"y":1.0,"z":1.0},"intensity":20.0},"type":"Light"}],"id":4},{"children":[],"components":[{"data":{"name":"Nothing"},"type":"Identification"},{"data":{"position":{"x":0.0,"y":6.949323654174805,"z":0.0},"previousPosition":{"x":0.0,"y":6.949323654174805,"z":0.0},"previousRotation":{"x":0.0,"y":-0.0,"z":0.0},"previousScale":{"x":1.0,"y":1.0,"z":1.0},"rotation":{"x":0.0,"y":-0.0,"z":0.0},"scale":{"x":1.0,"y":1.0,"z":1.0}},"type":"Transform"}],"id":5},{"children":[{"children":[],"components":[{"data":{"name":"Fox Box"},"type":"Identification"},{"data":{"position":{"x":-23.34000015258789,"y":-2.000002384185791,"z":13.65999984741211},"previousPosition":{"x":-23.34000015258789,"y":-2.000002384185791,"z":13.65999984741211},"previousRotation":{"x":1.001754879951477,"y":15.989482879638672,"z":1.0013483762741089},"previousScale":{"x":1.0,"y":1.0,"z":1.0},"rotation":{"x":1.001754879951477,"y":15.989482879638672,"z":1.0013483762741089},"scale":{"x":1.0,"y":1.0,"z":1.0}},"type":"Transform"},{"data":{"diff_coeff":{"x":2.0,"y":2.0,"z":2.0},"meshName":"Cube","selected":false,"spec_coeff":{"x":0.5,"y":0.5,"z":0.5},"spec_exponent":5.0},"type":"Material"},{"data":{"texturePath":"assets\\textures\\Fox.jpg"},"type":"Texture"}],"id":7},{"children":[],"components":[{"data":{"name":"Sphere"},"type":"Identification"},{"data":{"position":{"x":-23.00001335144043,"y":2.0000200271606445,"z":17.000064849853516},"previousPosition":{"x":-23.00001335144043,"y":2.0000200271606445,"z":17.000064849853516},"previousRotation":{"x":6.444730388466269e-05,"y":0.02797645516693592,"z":-0.00016049448458943516},"previousScale":{"x":1.0,"y":1.0,"z":1.0},"rotation":{"x":6.444730388466269e-05,"y":0.02797645516693592,"z":-0.00016049448458943516},"scale":{"x":1.0,"y":1.0,"z":1.0}},"type":"Transform"},{"data":{"acceleration":{"x":0.0,"y":0.0,"z":0.0},"rotationalAcceleration":{"x":0.0,"y":0.0,"z":0.0},"rotationalVelocity":{"x":0.0,"y":0.0,"z":0.0},"velocity":{"x":0.0,"y":0.0,"z":0.0}},"type":"RigidBody"},{"data":{"diff_coeff":{"x":2.0,"y":2.0,"z":2.0},"meshName":"Icosphere","selected":false,"spec_coeff":{"x":0.5,"y":0.5,"z":0.5},"spec_exponent":5.0},"type":"Material"}],"id":8},{"children":[],"components":[{"data":{"name":"Raccube"},"type":"Identification"},{"data":{"position":{"x":-26.6299991607666,"y":-1.9999845027923584,"z":16.90999984741211},"previousPosition":{"x":-26.6299991607666,"y":-1.9999845027923584,"z":16.90999984741211},"previousRotation":{"x":6.005803879816085e-05,"y":79.95783233642578,"z":1.581753349455539e-05},"previousScale":{"x":1.0,"y":1.0,"z":1.0},"rotation":{"x":6.005803879816085e-05,"y":79.95783233642578,"z":1.581753349455539e-05},"scale":{"x":1.0,"y":1.0,"z":1.0}},"type":"Transform"},{"data":{"diff_coeff":{"x":2.0,"y":2.0,"z":2.0},"meshName":"Cube","selected":false,"spec_coeff":{"x":0.5,"y":0.5,"z":0.5},"spec_exponent":5.0},"type":"Material"},{"data":{"texturePath":"assets\\textures\\Raccoon.jpg"},"type":"Texture"}],"id":9},{"children":[],"components":[{"data":{"name":"Kurisu"},"type":"Identification"},{"data":{"position":{"x":-26.149999618530273,"y":-1.0000100135803223,"z":13.920000076293945},"previousPosition":{"x":-26.149999618530273,"y":-1.0000100135803223,"z":13.920000076293945},"previousRotation":{"x":-0.001134563353843987,"y":44.9612922668457,"z":-2.3215996407088824e-05},"previousScale":{"x":1.0,"y":2.0,"z":1.0},"rotation":{"x":-0.001134563353843987,"y":44.9612922668457,"z":-2.3215996407088824e-05},"scale":{"x":1.0,"y":2.0,"z":1.0}},"type":"Transform"},{"data":{"diff_coeff":{"x":2.0,"y":2.0,"z":2.0},"meshName":"Cube","selected":false,"spec_coeff":{"x":0.5,"y":0.5,"z":0.5},"spec_exponent":5.0},"type":"Material"},{"data":{"texturePath":"assets\\textures\\Kurisu.png"},"type":"Texture"}],"id":10},{"children":[{"children":[],"components":[{"data":{"name":"Okayu2"},"type":"Identification"},{"data":{"position":{"x":-15.2400484085083,"y":-1.9999818801879883,"z":15.150110244750977},"previousPosition":{"x":-15.2400484085083,"y":-1.9999818801879883,"z":15.150110244750977},"previousRotation":{"x":-0.004455976188182831,"y":-44.943809509277344,"z":0.0019161419477313757},"previousScale":{"x":2.0,"y":1.0,"z":2.0},"rotation":{"x":-0.004455976188182831,"y":-44.943809509277344,"z":0.0019161419477313757},"scale":{"x":2.0,"y":1.0,"z":2.0}},"type":"Transform"},{"data":{"diff_coeff":{"x":2.0,"y":2.0,"z":2.0},"meshName":"Cube","selected":false,"spec_coeff":{"x":0.5,"y":0.5,"z":0.5},"spec_exponent":5.0},"type":"Material"},{"data":{"texturePath":"assets\\textures\\Okayu2.png"},"type":"Texture"}],"id":12}],"components":[{"data":{"name":"Okayu1"},"type":"Identification"},{"data":{"position":{"x":-15.239999771118164,"y":5.7220458984375e-06,"z":15.149999618530273},"previousPosition":{"x":-15.239999771118164,"y":5.7220458984375e-06,"z":15.149999618530273},"previousRotation":{"x":-0.0034927939996123314,"y":-22.914087295532227,"z":0.00016865960787981749},"previousScale":{"x":1.0,"y":1.0,"z":1.0},"rotation":{"x":-0.0034927939996123314,"y":-22.914087295532227,"z":0.00016865960787981749},"scale":{"x":1.0,"y":1.0,"z":1.0}},"type":"Transform"},{"data":{"diff_coeff":{"x":2.0,"y":2.0,"z":2.0},"meshName":"Cube","selected":false,"spec_coeff":{"x":0.5,"y":0.5,"z":0.5},"spec_exponent":5.0},"type":"Material"},{"data":{"texturePath":"assets\\textures\\Okayu1.jpg"},"type":"Texture"}],"id":11},{"children":[],"components":[{"data":{"name":"Light"},"type":"Identification"},{"data":{"position":{"x":-18.0,"y":4.0,"z":21.0},"previousPosition":{"x":-18.0,"y":4.0,"z":21.0},"previousRotation":{"x":0.0,"y":-0.0,"z":0.0},"previousScale":{"x":1.0,"y":1.0,"z":1.0},"rotation":{"x":0.0,"y":-0.0,"z":0.0},"scale":{"x":1.0,"y":1.0,"z":1.0}},"type":"Transform"},{"data":{"color":{"x":1.0,"y":1.0,"z":1.0},"intensity":20.0},"type":"Light"}],"id":13},{"children":[],"components":[{"data":{"name":"Nimi"},"type":"Identification"},{"data":{"position":{"x":-14.640000343322754,"y":-2.0,"z":21.649999618530273},"previousPosition":{"x":-14.640000343322754,"y":-2.0,"z":21.649999618530273},"previousRotation":{"x":-8.175359694773121e-11,"y":28.78499984741211,"z":0.00017878755170386285},"previousScale":{"x":1.0,"y":1.0,"z":1.0},"rotation":{"x":-8.175359694773121e-11,"y":28.78499984741211,"z":0.00017878755170386285},"scale":{"x":1.0,"y":1.0,"z":1.0}},"type":"Transform"},{"data":{"diff_coeff":{"x":2.0,"y":2.0,"z":2.0},"meshName":"Cube","selected":false,"spec_coeff":{"x":0.5,"y":0.5,"z":0.5},"spec_exponent":5.0},"type":"Material"},{"data":{"texturePath":"assets\\textures\\Nimi1.jpg"},"type":"Texture"}],"id":14}],"components":[{"data":{"name":"Floor"},"type":"Identification"},{"data":{"position":{"x":-20.0,"y":-4.0,"z":20.0},"previousPosition":{"x":-20.0,"y":-4.0,"z":20.0},"previousRotation":{"x":0.0,"y":0.0,"z":0.0},"previousScale":{"x":8.0,"y":1.0,"z":8.0},"rotation":{"x":0.0,"y":0.0,"z":0.0},"scale":{"x":8.0,"y":1.0,"z":8.0}},"type":"Transform"},{"data":{"diff_coeff":{"x":1.0,"y":0.9998999834060669,"z":0.9998999834060669},"meshName":"Cube","selected":false,"spec_coeff":{"x":0.9999515414237976,"y":0.9998999834060669,"z":1.0},"spec_exponent":10.0},"type":"Material"},{"data":{"texturePath":"assets\\textures\\Checker.jpg"},"type":"Texture"}],"id":6},{"children":[{"children":[],"components":[{"data":{"name":"Yellow Light"},"type":"Identification"},{"data":{"position":{"x":-34.27616882324219,"y":20.637144088745117,"z":-34.309165954589844},"previousPosition":{"x":-34.27616882324219,"y":20.637144088745117,"z":-34.309165954589844},"previousRotation":{"x":-33.1716423034668,"y":-6.717229843139648,"z":13.201322555541992},"previousScale":{"x":1.0,"y":1.0,"z":1.0},"rotation":{"x":-33.1716423034668,"y":-6.717229843139648,"z":13.201322555541992},"scale":{"x":1.0,"y":1.0,"z":1.0}},"type":"Transform"},{"data":{"diff_coeff":{"x":2.0,"y":2.0,"z":2.0},"meshName":"Cube","selected":false,"spec_coeff":{"x":0.5,"y":0.5,"z":0.5},"spec_exponent":5.0},"type":"Material"},{"data":{"color":{"x":1.0,"y":0.9171974658966064,"z":0.0},"intensity":38.0},"type":"Light"}],"id":16},{"children":[],"components":[{"data":{"name":"Pink Light"},"type":"Identification"},{"data":{"position":{"x":-71.34989166259766,"y":52.037567138671875,"z":-20.75168228149414},"previousPosition":{"x":-71.34989166259766,"y":52.037567138671875,"z":-20.75168228149414},"previousRotation":{"x":-37.92597579956055,"y":-4.138829231262207,"z":11.94156551361084},"previousScale":{"x":1.0,"y":1.0,"z":1.0},"rotation":{"x":-37.92597579956055,"y":-4.138829231262207,"z":11.94156551361084},"scale":{"x":1.0,"y":1.0,"z":1.0}},"type":"Transform"},{"data":{"diff_coeff":{"x":2.0,"y":2.0,"z":2.0},"meshName":"Cube","selected":false,"spec_coeff":{"x":0.5,"y":0.5,"z":0.5},"spec_exponent":5.0},"type":"Material"},{"data":{"color":{"x":0.91082763671875,"y":0.0,"z":1.0},"intensity":38.0},"type":"Light"}],"id":17},{"children":[],"components":[{"data":{"name":"Red Light"},"type":"Identification"},{"data":{"position":{"x":-101.46705627441406,"y":-11.857748031616211,"z":-8.647411346435547},"previousPosition":{"x":-101.46705627441406,"y":-11.857748031616211,"z":-8.647411346435547},"previousRotation":{"x":35.56391906738281,"y":-49.16304397583008,"z":161.56297302246094},"previousScale":{"x":0.10000000149011612,"y":0.10000000149011612,"z":0.10000000149011612},"rotation":{"x":35.56391906738281,"y":-49.16304397583008,"z":161.56297302246094},"scale":{"x":0.10000000149011612,"y":0.10000000149011612,"z":0.10000000149011612}},"type":"Transform"},{"data":{"diff_coeff":{"x":2.0,"y":2.0,"z":2.0},"meshName":"Cube","selected":false,"spec_coeff":{"x":0.5,"y":0.5,"z":0.5},"spec_exponent":5.0},"type":"Material"},{"data":{"color":{"x":1.0,"y":0.0,"z":0.0},"intensity":47.0},"type":"Light"}],"id":18},{"children":[],"components":[{"data":{"name":"Pink Light"},"type":"Identification"},{"data":{"position":{"x":-48.461158752441406,"y":1.7789759635925293,"z":-74.16993713378906},"previousPosition":{"x":-48.461158752441406,"y":1.7789759635925293,"z":-74.16993713378906},"previousRotation":{"x":-96.4188003540039,"y":-28.468505859375,"z":-11.555770874023438},"previousScale":{"x":1.0,"y":1.0,"z":1.0},"rotation":{"x":-96.4188003540039,"y":-28.468505859375,"z":-11.555770874023438},"scale":{"x":1.0,"y":1.0,"z":1.0}},"type":"Transform"},{"data":{"diff_coeff":{"x":2.0,"y":2.0,"z":2.0},"meshName":"Cube","selected":false,"spec_coeff":{"x":0.5,"y":0.5,"z":0.5},"spec_exponent":5.0},"type":"Material"},{"data":{"color":{"x":0.91082763671875,"y":0.0,"z":1.0},"intensity":38.0},"type":"Light"}],"id":19},{"children":[],"components":[{"data":{"name":"Yellow Light"},"type":"Identification"},{"data":{"position":{"x":-67.3504409790039,"y":16.11746597290039,"z":-10.098342895507813},"previousPosition":{"x":-67.3504409790039,"y":16.11746597290039,"z":-10.098342895507813},"previousRotation":{"x":31.623247146606445,"y":54.294456481933594,"z":174.39614868164063},"previousScale":{"x":1.0,"y":1.0,"z":1.0},"rotation":{"x":31.623247146606445,"y":54.294456481933594,"z":174.39614868164063},"scale":{"x":1.0,"y":1.0,"z":1.0}},"type":"Transform"},{"data":{"diff_coeff":{"x":2.0,"y":2.0,"z":2.0},"meshName":"Cube","selected":false,"spec_coeff":{"x":0.5,"y":0.5,"z":0.5},"spec_exponent":5.0},"type":"Material"},{"data":{"color":{"x":1.0,"y":0.9171974658966064,"z":0.0},"intensity":38.0},"type":"Light"}],"id":20},{"children":[],"components":[{"data":{"name":"Red Light"},"type":"Identification"},{"data":{"position":{"x":-78.39358520507813,"y":55.689979553222656,"z":-54.00763702392578},"previousPosition":{"x":-78.39358520507813,"y":55.689979553222656,"z":-54.00763702392578},"previousRotation":{"x":-127.53412628173828,"y":-18.271987915039063,"z":72.4556884765625},"previousScale":{"x":0.10000000149011612,"y":0.10000000149011612,"z":0.10000000149011612},"rotation":{"x":-127.53412628173828,"y":-18.271987915039063,"z":72.4556884765625},"scale":{"x":0.10000000149011612,"y":0.10000000149011612,"z":0.10000000149011612}},"type":"Transform"},{"data":{"diff_coeff":{"x":2.0,"y":2.0,"z":2.0},"meshName":"Cube","selected":false,"spec_coeff":{"x":0.5,"y":0.5,"z":0.5},"spec_exponent":5.0},"type":"Material"},{"data":{"color":{"x":1.0,"y":0.0,"z":0.0},"intensity":47.0},"type":"Light"}],"id":21},{"children":[],"components":[{"data":{"name":"Blue Light"},"type":"Identification"},{"data":{"position":{"x":-121.21928405761719,"y":4.793855667114258,"z":-63.166282653808594},"previousPosition":{"x":-121.21928405761719,"y":4.793855667114258,"z":-63.166282653808594},"previousRotation":{"x":61.130611419677734,"y":-68.57597351074219,"z":85.99520874023438},"previousScale":{"x":0.10000000149011612,"y":0.10000000149011612,"z":0.10000000149011612},"rotation":{"x":61.130611419677734,"y":-68.57597351074219,"z":85.99520874023438},"scale":{"x":0.10000000149011612,"y":0.10000000149011612,"z":0.10000000149011612}},"type":"Transform"},{"data":{"diff_coeff":{"x":2.0,"y":2.0,"z":2.0},"meshName":"Cube","selected":false,"spec_coeff":{"x":0.5,"y":0.5,"z":0.5},"spec_exponent":5.0},"type":"Material"},{"data":{"color":{"x":0.012738704681396484,"y":0.0,"z":1.0},"intensity":47.0},"type":"Light"}],"id":22}],"components":[{"data":{"name":"Globe"},"type":"Identification"},{"data":{"position":{"x":-79.0,"y":7.0,"z":-43.0},"previousPosition":{"x":-79.0,"y":7.0,"z":-43.0},"previousRotation":{"x":112286.3125,"y":208247.90625,"z":196.61866760253906},"previousScale":{"x":30.0,"y":30.0,"z":30.0},"rotation":{"x":112286.3125,"y":208247.90625,"z":196.61866760253906},"scale":{"x":30.0,"y":30.0,"z":30.0}},"type":"Transform"},{"data":{"acceleration":{"x":0.0,"y":0.0,"z":0.0},"rotationalAcceleration":{"x":0.0,"y":0.0,"z":0.0},"rotationalVelocity":{"x":5.0,"y":10.0,"z":0.0},"velocity":{"x":0.0,"y":0.0,"z":0.0}},"type":"RigidBody"},{"data":{"diff_coeff":{"x":0.15630578994750977,"y":0.0,"z":1.0},"meshName":"Icosphere","selected":false,"spec_coeff":{"x":0.9999101758003235,"y":0.9998999834060669,"z":1.0},"spec_exponent":10.0},"type":"Material"},{"data":{"texturePath":"assets\\textures\\Checker.jpg"},"type":"Texture"}],"id":15},{"children":[],"components":[{"data":{"name":"Nothing"},"type":"Identification"}],"id":23},{"children":[],"components":[{"data":{"name":"Name is [688615]"},"type":"Identification"},{"data":{"position":{"x":50.0,"y":5.0,"z":0.0},"previousPosition":{"x":50.0,"y":5.0,"z":0.0},"previousRotation":{"x":1.8310517072677612,"y":-8.783157348632813,"z":-6.756274700164795},"previousScale":{"x":0.9998350739479065,"y":1.999997854232788,"z":0.9998350739479065},"rotation":{"x":1.8310517072677612,"y":-8.783157348632813,"z":-6.756274700164795},"scale":{"x":0.9998350739479065,"y":1.999997854232788,"z":0.9998350739479065}},"type":"Transform"},{"data":{"diff_coeff":{"x":1.0,"y":1.0,"z":1.0},"meshName":"Cube","selected":false,"spec_coeff":{"x":1.0,"y":1.0,"z":1.0},"spec_exponent":10.0},"type":"Material"},{"data":{"env":0,"exit":0,"init":0,"path":"assets\\scripts\\randomname.lua","update":0},"type":"Script"},{"data":{"texturePath":"assets\\textures\\Kurisu.png"},"type":"Texture"}],"id":24},{"children":[],"components":[{"data":{"name":"Tornado Light"},"type":"Identification"},{"data":{"position":{"x":37.599998474121094,"y":4.900000095367432,"z":0.0},"previousPosition":{"x":37.599998474121094,"y":4.900000095367432,"z":0.0},"previousRotation":{"x":0.0,"y":0.0,"z":0.0},"previousScale":{"x":1.0,"y":1.0,"z":1.0},"rotation":{"x":0.0,"y":0.0,"z":0.0},"scale":{"x":1.0,"y":1.0,"z":1.0}},"type":"Transform"},{"data":{"diff_coeff":{"x":0.08917200565338135,"y":1.0,"z":0.0},"meshName":"Icosphere","selected":false,"spec_coeff":{"x":0.20382177829742432,"y":1.0,"z":0.0},"spec_exponent":5.0},"type":"Material"},{"data":{"color":{"x":0.0,"y":0.9808917045593262,"z":1.0},"intensity":29.000999450683594},"type":"Light"}],"id":25},{"children":[],"components":[{"data":{"name":"Name is [784068]"},"type":"Identification"},{"data":{"position":{"x":2.0,"y":4.453979969024658,"z":15.0},"previousPosition":{"x":2.0,"y":4.453979969024658,"z":15.0},"previousRotation":{"x":-3.5290603637695313,"y":-9.413683891296387,"z":-17.650657653808594},"previousScale":{"x":0.9998350739479065,"y":1.999997854232788,"z":0.9998350739479065},"rotation":{"x":-3.5290603637695313,"y":-9.413683891296387,"z":-17.650657653808594},"scale":{"x":0.9998350739479065,"y":1.999997854232788,"z":0.9998350739479065}},"type":"Transform"},{"data":{"acceleration":{"x":0.0,"y":0.0,"z":0.0},"rotationalAcceleration":{"x":0.0,"y":0.0,"z":0.0},"rotationalVelocity":{"x":0.0,"y":0.0,"z":0.0},"velocity":{"x":0.0,"y":1.9080840349197388,"z":0.0}},"type":"RigidBody"},{"data":{"diff_coeff":{"x":1.0,"y":1.0,"z":1.0},"meshName":"Cube","selected":false,"spec_coeff":{"x":1.0,"y":1.0,"z":1.0},"spec_exponent":5.0},"type":"Material"},{"data":{"env":0,"exit":0,"init":0,"path":"assets\\scripts\\up_and_down.lua","update":0},"type":"Script"},{"data":{"texturePath":"assets\\textures\\Kurisu.png"},"type":"Texture"}],"id":26},{"children":[],"components":[{"data":{"name":"Kurisu Rotating"},"type":"Identification"},{"data":{"position":{"x":44.30775451660156,"y":-5.824492454528809,"z":-11.470931053161621},"previousPosition":{"x":44.30775451660156,"y":-5.824492454528809,"z":-11.470931053161621},"previousRotation":{"x":10.778288841247559,"y":0.5803058743476868,"z":8.128868103027344},"previousScale":{"x":0.9998350739479065,"y":1.999997854232788,"z":0.9998350739479065},"rotation":{"x":10.778288841247559,"y":0.5803058743476868,"z":8.128868103027344},"scale":{"x":0.9998350739479065,"y":1.999997854232788,"z":0.9998350739479065}},"type":"Transform"},{"data":{"acceleration":{"x":0.0,"y":0.0,"z":0.0},"rotationalAcceleration":{"x":0.0,"y":0.0,"z":0.0},"rotationalVelocity":{"x":0.0,"y":0.0,"z":0.0},"velocity":{"x":10.778288841247559,"y":0.5803058743476868,"z":8.128868103027344}},"type":"RigidBody"},{"data":{"diff_coeff":{"x":1.0,"y":1.0,"z":1.0},"meshName":"Cube","selected":false,"spec_coeff":{"x":1.0,"y":1.0,"z":1.0},"spec_exponent":5.0},"type":"Material"},{"data":{"env":0,"exit":0,"init":0,"path":"assets\\scripts\\example.lua","update":0},"type":"Script"},{"data":{"texturePath":"assets\\textures\\Kurisu.png"},"type":"Texture"}],"id":27},{"children":[],"components":[{"data":{"name":"Kurisu Rotating"},"type":"Identification"},{"data":{"position":{"x":31.603227615356445,"y":10.47647476196289,"z":-4.946337699890137},"previousPosition":{"x":31.603227615356445,"y":10.47647476196289,"z":-4.946337699890137},"previousRotation":{"x":2.5428364276885986,"y":-0.24512912333011627,"z":-4.305111408233643},"previousScale":{"x":0.9998350739479065,"y":1.999997854232788,"z":0.9998350739479065},"rotation":{"x":2.5428364276885986,"y":-0.24512912333011627,"z":-4.305111408233643},"scale":{"x":0.9998350739479065,"y":1.999997854232788,"z":0.9998350739479065}},"type":"Transform"},{"data":{"acceleration":{"x":0.0,"y":0.0,"z":0.0},"rotationalAcceleration":{"x":0.0,"y":0.0,"z":0.0},"rotationalVelocity":{"x":0.0,"y":0.0,"z":0.0},"velocity":{"x":2.5428364276885986,"y":-0.24512912333011627,"z":-4.305111408233643}},"type":"RigidBody"},{"data":{"diff_coeff":{"x":1.0,"y":1.0,"z":1.0},"meshName":"Cube","selected":false,"spec_coeff":{"x":1.0,"y":1.0,"z":1.0},"spec_exponent":5.0},"type":"Material"},{"data":{"env":0,"exit":0,"init":0,"path":"assets\\scripts\\example.lua","update":0},"type":"Script"},{"data":{"texturePath":"assets\\textures\\Kurisu.png"},"type":"Texture"}],"id":28},{"children":[],"components":[{"data":{"name":"Kurisu Rotating"},"type":"Identification"},{"data":{"position":{"x":22.40382194519043,"y":0.8368644714355469,"z":-7.419360160827637},"previousPosition":{"x":22.40382194519043,"y":0.8368644714355469,"z":-7.419360160827637},"previousRotation":{"x":3.8142545223236084,"y":0.22319455444812775,"z":-6.457666873931885},"previousScale":{"x":0.9998350739479065,"y":1.999997854232788,"z":0.9998350739479065},"rotation":{"x":3.8142545223236084,"y":0.22319455444812775,"z":-6.457666873931885},"scale":{"x":0.9998350739479065,"y":1.999997854232788,"z":0.9998350739479065}},"type":"Transform"},{"data":{"acceleration":{"x":0.0,"y":0.0,"z":0.0},"rotationalAcceleration":{"x":0.0,"y":0.0,"z":0.0},"rotationalVelocity":{"x":0.0,"y":0.0,"z":0.0},"velocity":{"x":3.8142545223236084,"y":0.22319455444812775,"z":-6.457666873931885}},"type":"RigidBody"},{"data":{"diff_coeff":{"x":1.0,"y":1.0,"z":1.0},"meshName":"Cube","selected":false,"spec_coeff":{"x":1.0,"y":1.0,"z":1.0},"spec_exponent":5.0},"type":"Material"},{"data":{"env":0,"exit":0,"init":0,"path":"assets\\scripts\\example.lua","update":0},"type":"Script"},{"data":{"texturePath":"assets\\textures\\Kurisu.png"},"type":"Texture"}],"id":29},{"children":[],"components":[{"data":{"name":"Kurisu Rotating"},"type":"Identification"},{"data":{"position":{"x":44.68691635131836,"y":17.87916374206543,"z":-10.70602798461914},"previousPosition":{"x":44.68691635131836,"y":17.87916374206543,"z":-10.70602798461914},"previousRotation":{"x":10.059736251831055,"y":-0.5845766663551331,"z":7.58694314956665},"previousScale":{"x":0.9998350739479065,"y":1.999997854232788,"z":0.9998350739479065},"rotation":{"x":10.059736251831055,"y":-0.5845766663551331,"z":7.58694314956665},"scale":{"x":0.9998350739479065,"y":1.999997854232788,"z":0.9998350739479065}},"type":"Transform"},{"data":{"acceleration":{"x":0.0,"y":0.0,"z":0.0},"rotationalAcceleration":{"x":0.0,"y":0.0,"z":0.0},"rotationalVelocity":{"x":0.0,"y":0.0,"z":0.0},"velocity":{"x":10.059736251831055,"y":-0.5845766663551331,"z":7.58694314956665}},"type":"RigidBody"},{"data":{"diff_coeff":{"x":1.0,"y":1.0,"z":1.0},"meshName":"Cube","selected":false,"spec_coeff":{"x":1.0,"y":1.0,"z":1.0},"spec_exponent":5.0},"type":"Material"},{"data":{"env":0,"exit":0,"init":0,"path":"assets\\scripts\\example.lua","update":0},"type":"Script"},{"data":{"texturePath":"assets\\textures\\Kurisu.png"},"type":"Texture"}],"id":30},{"children":[],"components":[{"data":{"name":"Kurisu Rotating"},"type":"Identification"},{"data":{"position":{"x":33.10087966918945,"y":-3.172091484069824,"z":10.952880859375},"previousPosition":{"x":33.10087966918945,"y":-3.172091484069824,"z":10.952880859375},"previousRotation":{"x":-1.09528386592865,"y":6.854041576385498,"z":-0.49025824666023254},"previousScale":{"x":0.9998350739479065,"y":1.999997854232788,"z":0.9998350739479065},"rotation":{"x":-1.09528386592865,"y":6.854041576385498,"z":-0.49025824666023254},"scale":{"x":0.9998350739479065,"y":1.999997854232788,"z":0.9998350739479065}},"type":"Transform"},{"data":{"acceleration":{"x":0.0,"y":0.0,"z":0.0},"rotationalAcceleration":{"x":0.0,"y":0.0,"z":0.0},"rotationalVelocity":{"x":0.0,"y":0.0,"z":0.0},"velocity":{"x":-1.09528386592865,"y":6.854041576385498,"z":-0.49025824666023254}},"type":"RigidBody"},{"data":{"diff_coeff":{"x":1.0,"y":1.0,"z":1.0},"meshName":"Cube","selected":false,"spec_coeff":{"x":1.0,"y":1.0,"z":1.0},"spec_exponent":5.0},"type":"Material"},{"data":{"env":0,"exit":0,"init":0,"path":"assets\\scripts\\example.lua","update":0},"type":"Script"},{"data":{"texturePath":"assets\\textures\\Kurisu.png"},"type":"Texture"}],"id":31},{"children":[],"components":[{"data":{"name":"Kurisu Rotating"},"type":"Identification"},{"data":{"position":{"x":49.22194290161133,"y":16.063432693481445,"z":-4.291296005249023},"previousPosition":{"x":49.22194290161133,"y":16.063432693481445,"z":-4.291296005249023},"previousRotation":{"x":1.2740707397460938,"y":6.758060932159424,"z":4.002092361450195},"previousScale":{"x":0.9998350739479065,"y":1.999997854232788,"z":0.9998350739479065},"rotation":{"x":1.2740707397460938,"y":6.758060932159424,"z":4.002092361450195},"scale":{"x":0.9998350739479065,"y":1.999997854232788,"z":0.9998350739479065}},"type":"Transform"},{"data":{"acceleration":{"x":0.0,"y":0.0,"z":0.0},"rotationalAcceleration":{"x":0.0,"y":0.0,"z":0.0},"rotationalVelocity":{"x":0.0,"y":0.0,"z":0.0},"velocity":{"x":1.2740707397460938,"y":6.758060932159424,"z":4.002092361450195}},"type":"RigidBody"},{"data":{"diff_coeff":{"x":1.0,"y":1.0,"z":1.0},"meshName":"Cube","selected":false,"spec_coeff":{"x":1.0,"y":1.0,"z":1.0},"spec_exponent":5.0},"type":"Material"},{"data":{"env":0,"exit":0,"init":0,"path":"assets\\scripts\\example.lua","update":0},"type":"Script"},{"data":{"texturePath":"assets\\textures\\Kurisu.png"},"type":"Texture"}],"id":32},{"children":[],"components":[{"data":{"name":"Kurisu Rotating"},"type":"Identification"},{"data":{"position":{"x":44.30775451660156,"y":17.329206466674805,"z":-11.470931053161621},"previousPosition":{"x":44.30775451660156,"y":17.329206466674805,"z":-11.470931053161621},"previousRotation":{"x":10.778288841247559,"y":1.7681835889816284,"z":8.128868103027344},"previousScale":{"x":0.9998350739479065,"y":1.999997854232788,"z":0.9998350739479065},"rotation":{"x":10.778288841247559,"y":1.7681835889816284,"z":8.128868103027344},"scale":{"x":0.9998350739479065,"y":1.999997854232788,"z":0.9998350739479065}},"type":"Transform"},{"data":{"acceleration":{"x":0.0,"y":0.0,"z":0.0},"rotationalAcceleration":{"x":0.0,"y":0.0,"z":0.0},"rotationalVelocity":{"x":0.0,"y":0.0,"z":0.0},"velocity":{"x":10.778288841247559,"y":1.7681835889816284,"z":8.128868103027344}},"type":"RigidBody"},{"data":{"diff_coeff":{"x":1.0,"y":1.0,"z":1.0},"meshName":"Cube","selected":false,"spec_coeff":{"x":1.0,"y":1.0,"z":1.0},"spec_exponent":5.0},"type":"Material"},{"data":{"env":0,"exit":0,"init":0,"path":"assets\\scripts\\example.lua","update":0},"type":"Script"},{"data":{"texturePath":"assets\\textures\\Kurisu.png"},"type":"Texture"}],"id":33},{"children":[],"components":[{"data":{"name":"Kurisu Rotating"},"type":"Identification"},{"data":{"position":{"x":40.93414306640625,"y":16.86566925048828,"z":-11.561203956604004},"previousPosition":{"x":40.93414306640625,"y":16.86566925048828,"z":-11.561203956604004},"previousRotation":{"x":15.849617958068848,"y":-0.5311130881309509,"z":5.570423126220703},"previousScale":{"x":0.9998350739479065,"y":1.999997854232788,"z":0.9998350739479065},"rotation":{"x":15.849617958068848,"y":-0.5311130881309509,"z":5.570423126220703},"scale":{"x":0.9998350739479065,"y":1.999997854232788,"z":0.9998350739479065}},"type":"Transform"},{"data":{"acceleration":{"x":0.0,"y":0.0,"z":0.0},"rotationalAcceleration":{"x":0.0,"y":0.0,"z":0.0},"rotationalVelocity":{"x":0.0,"y":0.0,"z":0.0},"velocity":{"x":15.849617958068848,"y":-0.5311130881309509,"z":5.570423126220703}},"type":"RigidBody"},{"data":{"diff_coeff":{"x":1.0,"y":1.0,"z":1.0},"meshName":"Cube","selected":false,"spec_coeff":{"x":1.0,"y":1.0,"z":1.0},"spec_exponent":5.0},"type":"Material"},{"data":{"env":0,"exit":0,"init":0,"path":"assets\\scripts\\example.lua","update":0},"type":"Script"},{"data":{"texturePath":"assets\\textures\\Kurisu.png"},"type":"Texture"}],"id":34},{"children":[],"components":[{"data":{"name":"Kurisu Rotating"},"type":"Identification"},{"data":{"position":{"x":24.68018341064453,"y":-4.17629337310791,"z":3.6424942016601563},"previousPosition":{"x":24.68018341064453,"y":-4.17629337310791,"z":3.6424942016601563},"previousRotation":{"x":-6.937934875488281,"y":6.50309419631958,"z":-16.825725555419922},"previousScale":{"x":0.9998350739479065,"y":1.999997854232788,"z":0.9998350739479065},"rotation":{"x":-6.937934875488281,"y":6.50309419631958,"z":-16.825725555419922},"scale":{"x":0.9998350739479065,"y":1.999997854232788,"z":0.9998350739479065}},"type":"Transform"},{"data":{"acceleration":{"x":0.0,"y":0.0,"z":0.0},"rotationalAcceleration":{"x":0.0,"y":0.0,"z":0.0},"rotationalVelocity":{"x":0.0,"y":0.0,"z":0.0},"velocity":{"x":-6.937934875488281,"y":6.50309419631958,"z":-16.825725555419922}},"type":"RigidBody"},{"data":{"diff_coeff":{"x":1.0,"y":1.0,"z":1.0},"meshName":"Cube","selected":false,"spec_coeff":{"x":1.0,"y":1.0,"z":1.0},"spec_exponent":5.0},"type":"Material"},{"data":{"env":0,"exit":0,"init":0,"path":"assets\\scripts\\example.lua","update":0},"type":"Script"},{"data":{"texturePath":"assets\\textures\\Kurisu.png"},"type":"Texture"}],"id":35},{"children":[],"components":[{"data":{"name":"Kurisu Rotating"},"type":"Identification"},{"data":{"position":{"x":38.124874114990234,"y":2.8543381690979004,"z":13.277621269226074},"previousPosition":{"x":38.124874114990234,"y":2.8543381690979004,"z":13.277621269226074},"previousRotation":{"x":-9.613222122192383,"y":2.0010461807250977,"z":1.9041976928710938},"previousScale":{"x":0.9998350739479065,"y":1.999997854232788,"z":0.9998350739479065},"rotation":{"x":-9.613222122192383,"y":2.0010461807250977,"z":1.9041976928710938},"scale":{"x":0.9998350739479065,"y":1.999997854232788,"z":0.9998350739479065}},"type":"Transform"},{"data":{"acceleration":{"x":0.0,"y":0.0,"z":0.0},"rotationalAcceleration":{"x":0.0,"y":0.0,"z":0.0},"rotationalVelocity":{"x":0.0,"y":0.0,"z":0.0},"velocity":{"x":-9.613222122192383,"y":2.0010461807250977,"z":1.9041976928710938}},"type":"RigidBody"},{"data":{"diff_coeff":{"x":1.0,"y":1.0,"z":1.0},"meshName":"Cube","selected":false,"spec_coeff":{"x":1.0,"y":1.0,"z":1.0},"spec_exponent":5.0},"type":"Material"},{"data":{"env":0,"exit":0,"init":0,"path":"assets\\scripts\\example.lua","update":0},"type":"Script"},{"data":{"texturePath":"assets\\textures\\Kurisu.png"},"type":"Texture"}],"id":36},{"children":[],"components":[{"data":{"name":"Kurisu Rotating"},"type":"Identification"},{"data":{"position":{"x":47.50815963745117,"y":-6.470953941345215,"z":-7.588578701019287},"previousPosition":{"x":47.50815963745117,"y":-6.470953941345215,"z":-7.588578701019287},"previousRotation":{"x":4.509274482727051,"y":8.128868103027344,"z":6.364467144012451},"previousScale":{"x":0.9998350739479065,"y":1.999997854232788,"z":0.9998350739479065},"rotation":{"x":4.509274482727051,"y":8.128868103027344,"z":6.364467144012451},"scale":{"x":0.9998350739479065,"y":1.999997854232788,"z":0.9998350739479065}},"type":"Transform"},{"data":{"acceleration":{"x":0.0,"y":0.0,"z":0.0},"rotationalAcceleration":{"x":0.0,"y":0.0,"z":0.0},"rotationalVelocity":{"x":0.0,"y":0.0,"z":0.0},"velocity":{"x":4.509274482727051,"y":8.128868103027344,"z":6.364467144012451}},"type":"RigidBody"},{"data":{"diff_coeff":{"x":1.0,"y":1.0,"z":1.0},"meshName":"Cube","selected":false,"spec_coeff":{"x":1.0,"y":1.0,"z":1.0},"spec_exponent":5.0},"type":"Material"},{"data":{"env":0,"exit":0,"init":0,"path":"assets\\scripts\\example.lua","update":0},"type":"Script"},{"data":{"texturePath":"assets\\textures\\Kurisu.png"},"type":"Texture"}],"id":37},{"children":[],"components":[{"data":{"name":"Kurisu Rotating"},"type":"Identification"},{"data":{"position":{"x":48.08150863647461,"y":14.48286247253418,"z":-5.837240219116211},"previousPosition":{"x":48.08150863647461,"y":14.48286247253418,"z":-5.837240219116211},"previousRotation":{"x":3.468672513961792,"y":5.792623519897461,"z":4.895744323730469},"previousScale":{"x":0.9998350739479065,"y":1.999997854232788,"z":0.9998350739479065},"rotation":{"x":3.468672513961792,"y":5.792623519897461,"z":4.895744323730469},"scale":{"x":0.9998350739479065,"y":1.999997854232788,"z":0.9998350739479065}},"type":"Transform"},{"data":{"acceleration":{"x":0.0,"y":0.0,"z":0.0},"rotationalAcceleration":{"x":0.0,"y":0.0,"z":0.0},"rotationalVelocity":{"x":0.0,"y":0.0,"z":0.0},"velocity":{"x":3.468672513961792,"y":5.792623519897461,"z":4.895744323730469}},"type":"RigidBody"},{"data":{"diff_coeff":{"x":1.0,"y":1.0,"z":1.0},"meshName":"Cube","selected":false,"spec_coeff":{"x":1.0,"y":1.0,"z":1.0},"spec_exponent":5.0},"type":"Material"},{"data":{"env":0,"exit":0,"init":0,"path":"assets\\scripts\\example.lua","update":0},"type":"Script"},{"data":{"texturePath":"assets\\textures\\Kurisu.png"},"type":"Texture"}],"id":38},{"children":[],"components":[{"data":{"name":"Kurisu Rotating"},"type":"Identification"},{"data":{"position":{"x":36.09922409057617,"y":17.329206466674805,"z":-11.656635284423828},"previousPosition":{"x":36.09922409057617,"y":17.329206466674805,"z":-11.656635284423828},"previousRotation":{"x":20.990699768066406,"y":1.7681835889816284,"z":0.6249447464942932},"previousScale":{"x":0.9998350739479065,"y":1.999997854232788,"z":0.9998350739479065},"rotation":{"x":20.990699768066406,"y":1.7681835889816284,"z":0.6249447464942932},"scale":{"x":0.9998350739479065,"y":1.999997854232788,"z":0.9998350739479065}},"type":"Transform"},{"data":{"acceleration":{"x":0.0,"y":0.0,"z":0.0},"rotationalAcceleration":{"x":0.0,"y":0.0,"z":0.0},"rotationalVelocity":{"x":0.0,"y":0.0,"z":0.0},"velocity":{"x":20.990699768066406,"y":1.7681835889816284,"z":0.6249447464942932}},"type":"RigidBody"},{"data":{"diff_coeff":{"x":1.0,"y":1.0,"z":1.0},"meshName":"Cube","selected":false,"spec_coeff":{"x":1.0,"y":1.0,"z":1.0},"spec_exponent":5.0},"type":"Material"},{"data":{"env":0,"exit":0,"init":0,"path":"assets\\scripts\\example.lua","update":0},"type":"Script"},{"data":{"texturePath":"assets\\textures\\Kurisu.png"},"type":"Texture"}],"id":39},{"children":[],"components":[{"data":{"name":"Kurisu Rotating"},"type":"Identification"},{"data":{"position":{"x":49.33198547363281,"y":6.195016384124756,"z":-3.678051710128784},"previousPosition":{"x":49.33198547363281,"y":6.195016384124756,"z":-3.678051710128784},"previousRotation":{"x":1.0920605659484863,"y":1.8866618871688843,"z":3.4303648471832275},"previousScale":{"x":0.9998350739479065,"y":1.999997854232788,"z":0.9998350739479065},"rotation":{"x":1.0920605659484863,"y":1.8866618871688843,"z":3.4303648471832275},"scale":{"x":0.9998350739479065,"y":1.999997854232788,"z":0.9998350739479065}},"type":"Transform"},{"data":{"acceleration":{"x":0.0,"y":0.0,"z":0.0},"rotationalAcceleration":{"x":0.0,"y":0.0,"z":0.0},"rotationalVelocity":{"x":0.0,"y":0.0,"z":0.0},"velocity":{"x":1.0920605659484863,"y":1.8866618871688843,"z":3.4303648471832275}},"type":"RigidBody"},{"data":{"diff_coeff":{"x":1.0,"y":1.0,"z":1.0},"meshName":"Cube","selected":false,"spec_coeff":{"x":1.0,"y":1.0,"z":1.0},"spec_exponent":5.0},"type":"Material"},{"data":{"env":0,"exit":0,"init":0,"path":"assets\\scripts\\example.lua","update":0},"type":"Script"},{"data":{"texturePath":"assets\\textures\\Kurisu.png"},"type":"Texture"}],"id":40},{"children":[],"components":[{"data":{"name":"Kurisu Rotating"},"type":"Identification"},{"data":{"position":{"x":27.923006057739258,"y":-2.5883736610412598,"z":-5.9352216720581055},"previousPosition":{"x":27.923006057739258,"y":-2.5883736610412598,"z":-5.9352216720581055},"previousRotation":{"x":3.051403760910034,"y":6.364467144012451,"z":-5.166133403778076},"previousScale":{"x":0.9998350739479065,"y":1.999997854232788,"z":0.9998350739479065},"rotation":{"x":3.051403760910034,"y":6.364467144012451,"z":-5.166133403778076},"scale":{"x":0.9998350739479065,"y":1.999997854232788,"z":0.9998350739479065}},"type":"Transform"},{"data":{"acceleration":{"x":0.0,"y":0.0,"z":0.0},"rotationalAcceleration":{"x":0.0,"y":0.0,"z":0.0},"rotationalVelocity":{"x":0.0,"y":0.0,"z":0.0},"velocity":{"x":3.051403760910034,"y":6.364467144012451,"z":-5.166133403778076}},"type":"RigidBody"},{"data":{"diff_coeff":{"x":1.0,"y":1.0,"z":1.0},"meshName":"Cube","selected":false,"spec_coeff":{"x":1.0,"y":1.0,"z":1.0},"spec_exponent":5.0},"type":"Material"},{"data":{"env":0,"exit":0,"init":0,"path":"assets\\scripts\\example.lua","update":0},"type":"Script"},{"data":{"texturePath":"assets\\textures\\Kurisu.png"},"type":"Texture"}],"id":41},{"children":[],"components":[{"data":{"name":"Kurisu Rotating"},"type":"Identification"},{"data":{"position":{"x":38.77908706665039,"y":15.273272514343262,"z":9.907142639160156},"previousPosition":{"x":38.77908706665039,"y":15.273272514343262,"z":9.907142639160156},"previousRotation":{"x":-3.9746437072753906,"y":6.2753424644470215,"z":-0.4496743381023407},"previousScale":{"x":0.9998350739479065,"y":1.999997854232788,"z":0.9998350739479065},"rotation":{"x":-3.9746437072753906,"y":6.2753424644470215,"z":-0.4496743381023407},"scale":{"x":0.9998350739479065,"y":1.999997854232788,"z":0.9998350739479065}},"type":"Transform"},{"data":{"acceleration":{"x":0.0,"y":0.0,"z":0.0},"rotationalAcceleration":{"x":0.0,"y":0.0,"z":0.0},"rotationalVelocity":{"x":0.0,"y":0.0,"z":0.0},"velocity":{"x":-3.9746437072753906,"y":6.2753424644470215,"z":-0.4496743381023407}},"type":"RigidBody"},{"data":{"diff_coeff":{"x":1.0,"y":1.0,"z":1.0},"meshName":"Cube","selected":false,"spec_coeff":{"x":1.0,"y":1.0,"z":1.0},"spec_exponent":5.0},"type":"Material"},{"data":{"env":0,"exit":0,"init":0,"path":"assets\\scripts\\example.lua","update":0},"type":"Script"},{"data":{"texturePath":"assets\\textures\\Kurisu.png"},"type":"Texture"}],"id":42}],"sceneData":{"entityCount":28}}